flanautils/__init__.py
flanautils/asyncs.py
flanautils/constants.py
flanautils/exceptions.py
flanautils/functions.py
flanautils/images.py
flanautils/iterables.py
flanautils/maths.py
flanautils/medias.py
flanautils/oss.py
flanautils/requests.py
flanautils/strings.py
flanautils/data_structures/__init__.py
flanautils/data_structures/bi_dict.py
flanautils/data_structures/ordered_set.py
flanautils/models/__init__.py
flanautils/models/bases.py
flanautils/models/database.py
flanautils/models/enums.py
flanautils/models/media.py
flanautils/models/plotly_charts.py
flanautils/models/score_match.py
flanautils/models/time_units.py
flanautils/resources/plotly_es.js
flanautils-1.8.1.dist-info/LICENSE
flanautils-1.8.1.dist-info/METADATA
flanautils-1.8.1.dist-info/WHEEL
flanautils-1.8.1.dist-info/top_level.txt
flanautils-1.8.1.dist-info/RECORD
