Metadata-Version: 2.1
Name: flanautils
Version: 1.8.1
Summary: Set of utilities of all kinds to develop python projects.
Author: AlberLC
License: MIT License
Project-URL: Homepage, https://github.com/AlberLC/flanautils
Classifier: Programming Language :: Python :: 3.10
Requires-Python: >=3.10
License-File: LICENSE
Requires-Dist: aiohttp
Requires-Dist: browser-cookie3
Requires-Dist: jeepney
Requires-Dist: jellyfish
Requires-Dist: mss
Requires-Dist: numpy
Requires-Dist: opencv-python
Requires-Dist: pymongo
Requires-Dist: plotly
Requires-Dist: sympy
Requires-Dist: kaleido
